intelliheal/__init__.py
intelliheal/config.py
intelliheal/dataset_prompts.py
intelliheal/decorator.py
intelliheal/driver_proxy.py
intelliheal/healer.py
intelliheal/llm_providers.py
intelliheal/pytest_plugin.py
intelliheal/recorder.py
intelliheal/interactions/assertions.py
intelliheal/interactions/mobile.py
intelliheal/interactions/web.py
intelliheal-0.1.8.dist-info/licenses/LICENSE
intelliheal-0.1.8.dist-info/METADATA
intelliheal-0.1.8.dist-info/WHEEL
intelliheal-0.1.8.dist-info/entry_points.txt
intelliheal-0.1.8.dist-info/top_level.txt
intelliheal-0.1.8.dist-info/RECORD
