Metadata-Version: 2.4
Name: IntelliHeal
Version: 0.1.8
Summary: AI-powered self-healing library for Selenium/Appium tests
Author-email: Didit Setiawan <didit@pintu.co.id>
Maintainer-email: Didit Setiawan <didit@pintu.co.id>
License: MIT
Project-URL: Homepage, https://github.com/IntelliHeal/intelliheal-pytest
Project-URL: Repository, https://github.com/IntelliHeal/intelliheal-pytest
Project-URL: Bug Tracker, https://github.com/IntelliHeal/intelliheal-pytest/issues
Project-URL: Documentation, https://intelliheal-pytest.readthedocs.io
Project-URL: Changelog, https://github.com/IntelliHeal/intelliheal-pytest/blob/main/CHANGELOG.md
Keywords: pytest,testing,automation,ai,healing,selenium,web,mobile,appium
Classifier: Development Status :: 3 - Alpha
Classifier: Framework :: Pytest
Classifier: Intended Audience :: Developers
Classifier: License :: OSI Approved :: MIT License
Classifier: Operating System :: OS Independent
Classifier: Programming Language :: Python :: 3
Classifier: Programming Language :: Python :: 3.10
Classifier: Programming Language :: Python :: 3.11
Classifier: Programming Language :: Python :: 3.12
Classifier: Topic :: Software Development :: Testing
Classifier: Topic :: Software Development :: Quality Assurance
Classifier: Topic :: Internet :: WWW/HTTP :: Browsers
Requires-Python: >=3.10
License-File: LICENSE
Requires-Dist: pytest
Requires-Dist: selenium
Requires-Dist: Appium-Python-Client
Requires-Dist: anthropic
Requires-Dist: openai
Requires-Dist: google-generativeai
Requires-Dist: groq
Requires-Dist: psycopg2-binary
Provides-Extra: dev
Requires-Dist: black>=22.0.0; extra == "dev"
Requires-Dist: isort>=5.10.0; extra == "dev"
Requires-Dist: flake8>=4.0.0; extra == "dev"
Requires-Dist: mypy>=0.950; extra == "dev"
Requires-Dist: pre-commit>=2.17.0; extra == "dev"
Requires-Dist: pytest-cov>=3.0.0; extra == "dev"
Requires-Dist: pytest-xdist>=2.5.0; extra == "dev"
Provides-Extra: test
Requires-Dist: pytest-cov>=3.0.0; extra == "test"
Requires-Dist: pytest-xdist>=2.5.0; extra == "test"
Requires-Dist: coverage>=6.0.0; extra == "test"
Provides-Extra: docs
Requires-Dist: sphinx>=4.0.0; extra == "docs"
Requires-Dist: sphinx-rtd-theme>=1.0.0; extra == "docs"
Provides-Extra: all
Requires-Dist: intelliheal-pytest[dev,docs,test]; extra == "all"
Dynamic: license-file
